fsnotify/__init__.py
fsnotify/scandir_vendored.py
fsnotify-0.2.1.dist-info/LICENSE
fsnotify-0.2.1.dist-info/METADATA
fsnotify-0.2.1.dist-info/WHEEL
fsnotify-0.2.1.dist-info/top_level.txt
fsnotify-0.2.1.dist-info/RECORD
