Metadata-Version: 2.1
Name: fsnotify
Version: 0.2.1
Summary: Simple file watching
Home-page: https://github.com/fabioz/fsnotify
Author: Fabio Zadrozny
Author-email: fabiofz@gmail.com
License: MIT license
Keywords: fsnotify filesystem notifications watchdog watchgod
Platform: UNKNOWN
Classifier: Development Status :: 2 - Pre-Alpha
Classifier: Intended Audience :: Developers
Classifier: License :: OSI Approved :: MIT License
Classifier: Natural Language :: English
Classifier: Programming Language :: Python :: 2
Classifier: Programming Language :: Python :: 2.7
Classifier: Programming Language :: Python :: 3
Classifier: Programming Language :: Python :: 3.5
Classifier: Programming Language :: Python :: 3.6
Classifier: Programming Language :: Python :: 3.7
Classifier: Programming Language :: Python :: 3.8
Requires-Python: >=2.7,!=3.0.*,!=3.1.*,!=3.2.*,!=3.3.*
Provides-Extra: test
Provides-Extra: dev
